bsmodals/__init__.py
bsmodals/static/bsmodals/bsmodals.js
bsmodals/static/bsmodals/restapi.js
bsmodals/templates/bsmodals/alert.html
bsmodals/templates/bsmodals/confirm.html
bsmodals/templates/bsmodals/entry.html
bsmodals/templates/bsmodals/error.html
bsmodals/templates/bsmodals/form.html
bsmodals/templates/bsmodals/generic.html
django_bstrap_modals-2.4.0.dist-info/LICENSE
django_bstrap_modals-2.4.0.dist-info/METADATA
django_bstrap_modals-2.4.0.dist-info/WHEEL
django_bstrap_modals-2.4.0.dist-info/top_level.txt
django_bstrap_modals-2.4.0.dist-info/RECORD
