Metadata-Version: 2.1
Name: django-bstrap-modals
Version: 2.4.0
Summary: Template and Javascript tools for working with Bootstrap 4 Modals
Home-page: https://github.com/cltrudeau/django-bstrap-modals
Author: Christopher Trudeau
Author-email: ctrudeau+pypi@arsensa.com
License: MIT
Keywords: django,bootstrap,modal
Platform: UNKNOWN
Classifier: Development Status :: 4 - Beta
Classifier: Environment :: Web Environment
Classifier: Intended Audience :: Developers
Classifier: License :: OSI Approved :: MIT License
Classifier: Operating System :: OS Independent
Classifier: Programming Language :: Python :: 3.6
Classifier: Programming Language :: Python :: 3.7
Classifier: Programming Language :: Python :: 3.8
Classifier: Topic :: Software Development :: Libraries :: Application Frameworks
Classifier: Topic :: Software Development :: Libraries :: Python Modules
Requires-Dist: Django (>=2.2.0)
